cve_2022_41343/__init__.py
cve_2022_41343/main.py
cve_2022_41343-1.0.0.dist-info/LICENSE
cve_2022_41343-1.0.0.dist-info/METADATA
cve_2022_41343-1.0.0.dist-info/WHEEL
cve_2022_41343-1.0.0.dist-info/entry_points.txt
cve_2022_41343-1.0.0.dist-info/top_level.txt
cve_2022_41343-1.0.0.dist-info/RECORD
