Metadata-Version: 2.1
Name: cve-2022-41343
Version: 1.0.0
Summary: Python Exploit for CVE-2022-41343 (dompdf RCE)
Author-email: Brandon Kreisel <BKreisel@users.noreply.github.com>
Project-URL: Homepage, https://github.com/BKreisel/CVE-2022-41343
Project-URL: Bug Tracker, https://github.com/BKreisel/CVE-2022-41343/issues
Classifier: Programming Language :: Python :: 3
Classifier: License :: OSI Approved :: MIT License
Classifier: Operating System :: OS Independent
Requires-Python: >=3.8
License-File: LICENSE
Requires-Dist: rich
